spice_to_sch/__init__.py
spice_to_sch/cli_def.py
spice_to_sch/constants.py
spice_to_sch/main.py
spice_to_sch/models.py
spice_to_sch-0.1.3.dist-info/METADATA
spice_to_sch-0.1.3.dist-info/WHEEL
spice_to_sch-0.1.3.dist-info/entry_points.txt
spice_to_sch-0.1.3.dist-info/RECORD
