Metadata-Version: 2.4
Name: spice-to-sch
Version: 0.1.3
Summary: A CLI to convert SkyWater SKY130 spice files into xschem .sch files.
Author-email: Eliah Reeves <ereeclimb@gmail.com>
Requires-Python: >=3.13
